ptext.py
ptext-1.1.0.dist-info/WHEEL
ptext-1.1.0.dist-info/METADATA
ptext-1.1.0.dist-info/RECORD
