Metadata-Version: 2.1
Name: ptext
Version: 1.1.0
Summary: Makes printing effect (ptext.printing("your text", delay_not_necessary))
Author: TimoXBeR
Author-email: bertim20102@gmail.com
Requires-Python: >=3.0,<4.0
Classifier: Programming Language :: Python :: 3
Classifier: Programming Language :: Python :: 3.10
Classifier: Programming Language :: Python :: 3.4
Classifier: Programming Language :: Python :: 3.5
Classifier: Programming Language :: Python :: 3.6
Classifier: Programming Language :: Python :: 3.7
Classifier: Programming Language :: Python :: 3.8
Classifier: Programming Language :: Python :: 3.9
